Metadata-Version: 2.1
Name: autoschedule
Version: 1.0
Summary: Generate schedule, talks, speakers page automatically like official Pycon thailand 2019 website: https://th.pycon.org
Home-page: https://github.com/Chomtana/autoschedule
Author: Chomtana
Author-email: Chomtana001@gmail.com
License: MIT
Keywords: autoschedule,schedule,generator,codegenerator,schedulepage,talks,talkspage,speakers,speakerspage,pycon
Platform: UNKNOWN
